COPYING.txt
MANIFEST.in
README.rst
pyinstaller-gui.py
pyinstaller.py
pyproject.toml
requirements.txt
setup.cfg
setup.py
PyInstaller/__init__.py
PyInstaller/__main__.py
PyInstaller/compat.py
PyInstaller/config.py
PyInstaller/configure.py
PyInstaller/log.py
PyInstallerCustom.egg-info/PKG-INFO
PyInstallerCustom.egg-info/SOURCES.txt
PyInstallerCustom.egg-info/dependency_links.txt
PyInstallerCustom.egg-info/entry_points.txt
PyInstallerCustom.egg-info/not-zip-safe
PyInstallerCustom.egg-info/requires.txt
PyInstallerCustom.egg-info/top_level.txt
PyInstaller/archive/__init__.py
PyInstaller/archive/pyz_crypto.py
PyInstaller/archive/readers.py
PyInstaller/archive/writers.py
PyInstaller/bootloader/Darwin-64bit/run
PyInstaller/bootloader/Darwin-64bit/run_d
PyInstaller/bootloader/Darwin-64bit/runw
PyInstaller/bootloader/Darwin-64bit/runw_d
PyInstaller/bootloader/Linux-32bit/run
PyInstaller/bootloader/Linux-32bit/run_d
PyInstaller/bootloader/Linux-64bit/run
PyInstaller/bootloader/Linux-64bit/run_d
PyInstaller/bootloader/Windows-32bit/run.exe
PyInstaller/bootloader/Windows-32bit/run_d.exe
PyInstaller/bootloader/Windows-32bit/runw.exe
PyInstaller/bootloader/Windows-32bit/runw_d.exe
PyInstaller/bootloader/Windows-64bit/run.exe
PyInstaller/bootloader/Windows-64bit/run_d.exe
PyInstaller/bootloader/Windows-64bit/runw.exe
PyInstaller/bootloader/Windows-64bit/runw_d.exe
PyInstaller/bootloader/images/github_logo.png
PyInstaller/bootloader/images/icon-console.icns
PyInstaller/bootloader/images/icon-console.ico
PyInstaller/bootloader/images/icon-console.svg
PyInstaller/bootloader/images/icon-windowed.icns
PyInstaller/bootloader/images/icon-windowed.ico
PyInstaller/bootloader/images/icon-windowed.svg
PyInstaller/building/__init__.py
PyInstaller/building/api.py
PyInstaller/building/build_main.py
PyInstaller/building/datastruct.py
PyInstaller/building/imphook.py
PyInstaller/building/imphookapi.py
PyInstaller/building/makespec.py
PyInstaller/building/osx.py
PyInstaller/building/templates.py
PyInstaller/building/toc_conversion.py
PyInstaller/building/utils.py
PyInstaller/depend/__init__.py
PyInstaller/depend/analysis.py
PyInstaller/depend/bindepend.py
PyInstaller/depend/dylib.py
PyInstaller/depend/utils.py
PyInstaller/fake-modules/site.py
PyInstaller/hooks/__init__.py
tests/functional/modules/nspkg1-pkg/nspkg1_aaa.egg/EGG-INFO/PKG-INFO
tests/functional/modules/nspkg1-pkg/nspkg1_aaa.egg/EGG-INFO/SOURCES.txt
tests/functional/modules/nspkg1-pkg/nspkg1_aaa.egg/EGG-INFO/dependency_links.txt
tests/functional/modules/nspkg1-pkg/nspkg1_aaa.egg/EGG-INFO/namespace_packages.txt
tests/functional/modules/nspkg1-pkg/nspkg1_aaa.egg/EGG-INFO/not-zip-safe
tests/functional/modules/nspkg1-pkg/nspkg1_aaa.egg/EGG-INFO/top_level.txt
tests/functional/modules/nspkg1-pkg/nspkg1_ccc.egg/EGG-INFO/PKG-INFO
tests/functional/modules/nspkg1-pkg/nspkg1_ccc.egg/EGG-INFO/SOURCES.txt
tests/functional/modules/nspkg1-pkg/nspkg1_ccc.egg/EGG-INFO/dependency_links.txt
tests/functional/modules/nspkg1-pkg/nspkg1_ccc.egg/EGG-INFO/namespace_packages.txt
tests/functional/modules/nspkg1-pkg/nspkg1_ccc.egg/EGG-INFO/not-zip-safe
tests/functional/modules/nspkg1-pkg/nspkg1_ccc.egg/EGG-INFO/top_level.txt
tests/functional/modules/nspkg3-pkg/nspkg3_aaa.egg/EGG-INFO/PKG-INFO
tests/functional/modules/nspkg3-pkg/nspkg3_aaa.egg/EGG-INFO/SOURCES.txt
tests/functional/modules/nspkg3-pkg/nspkg3_aaa.egg/EGG-INFO/dependency_links.txt
tests/functional/modules/nspkg3-pkg/nspkg3_aaa.egg/EGG-INFO/namespace_packages.txt
tests/functional/modules/nspkg3-pkg/nspkg3_aaa.egg/EGG-INFO/not-zip-safe
tests/functional/modules/nspkg3-pkg/nspkg3_aaa.egg/EGG-INFO/top_level.txt
tests/functional/modules/nspkg3-pkg/nspkg3_ccc.egg/EGG-INFO/PKG-INFO
tests/functional/modules/nspkg3-pkg/nspkg3_ccc.egg/EGG-INFO/SOURCES.txt
tests/functional/modules/nspkg3-pkg/nspkg3_ccc.egg/EGG-INFO/dependency_links.txt
tests/functional/modules/nspkg3-pkg/nspkg3_ccc.egg/EGG-INFO/namespace_packages.txt
tests/functional/modules/nspkg3-pkg/nspkg3_ccc.egg/EGG-INFO/not-zip-safe
tests/functional/modules/nspkg3-pkg/nspkg3_ccc.egg/EGG-INFO/top_level.txt
tests/functional/modules/pyi_egg_unzipped.egg/EGG-INFO/PKG-INFO
tests/functional/modules/pyi_egg_unzipped.egg/EGG-INFO/SOURCES.txt
tests/functional/modules/pyi_egg_unzipped.egg/EGG-INFO/dependency_links.txt
tests/functional/modules/pyi_egg_unzipped.egg/EGG-INFO/not-zip-safe
tests/functional/modules/pyi_egg_unzipped.egg/EGG-INFO/top_level.txt
tests/unit/test_modulegraph/testdata/nspkg/distribute-0.6.10/child/nameduser-1.5-py2.6.egg-info/PKG-INFO
tests/unit/test_modulegraph/testdata/nspkg/distribute-0.6.10/child/nameduser-1.5-py2.6.egg-info/SOURCES.txt
tests/unit/test_modulegraph/testdata/nspkg/distribute-0.6.10/child/nameduser-1.5-py2.6.egg-info/dependency_links.txt
tests/unit/test_modulegraph/testdata/nspkg/distribute-0.6.10/child/nameduser-1.5-py2.6.egg-info/namespace_packages.txt
tests/unit/test_modulegraph/testdata/nspkg/distribute-0.6.10/child/nameduser-1.5-py2.6.egg-info/top_level.txt
tests/unit/test_modulegraph/testdata/nspkg/distribute-0.6.10/parent/namedpkg-1.0-py2.6.egg-info/PKG-INFO
tests/unit/test_modulegraph/testdata/nspkg/distribute-0.6.10/parent/namedpkg-1.0-py2.6.egg-info/SOURCES.txt
tests/unit/test_modulegraph/testdata/nspkg/distribute-0.6.10/parent/namedpkg-1.0-py2.6.egg-info/dependency_links.txt
tests/unit/test_modulegraph/testdata/nspkg/distribute-0.6.10/parent/namedpkg-1.0-py2.6.egg-info/namespace_packages.txt
tests/unit/test_modulegraph/testdata/nspkg/distribute-0.6.10/parent/namedpkg-1.0-py2.6.egg-info/top_level.txt
tests/unit/test_modulegraph/testdata/nspkg/distribute-0.6.12/child/nameduser-1.5-py2.5.egg-info/PKG-INFO
tests/unit/test_modulegraph/testdata/nspkg/distribute-0.6.12/child/nameduser-1.5-py2.5.egg-info/SOURCES.txt
tests/unit/test_modulegraph/testdata/nspkg/distribute-0.6.12/child/nameduser-1.5-py2.5.egg-info/dependency_links.txt
tests/unit/test_modulegraph/testdata/nspkg/distribute-0.6.12/child/nameduser-1.5-py2.5.egg-info/namespace_packages.txt
